setup.py
src/xdevice/__init__.py
src/xdevice/__main__.py
src/xdevice.egg-info/PKG-INFO
src/xdevice.egg-info/SOURCES.txt
src/xdevice.egg-info/dependency_links.txt
src/xdevice.egg-info/entry_points.txt
src/xdevice.egg-info/not-zip-safe
src/xdevice.egg-info/requires.txt
src/xdevice.egg-info/top_level.txt
src/xdevice/_core/__init__.py
src/xdevice/_core/common.py
src/xdevice/_core/constants.py
src/xdevice/_core/error.py
src/xdevice/_core/exception.py
src/xdevice/_core/interface.py
src/xdevice/_core/logger.py
src/xdevice/_core/plugin.py
src/xdevice/_core/utils.py
src/xdevice/_core/variables.py
src/xdevice/_core/analysis/__init__.py
src/xdevice/_core/analysis/db.py
src/xdevice/_core/analysis/testing.py
src/xdevice/_core/analysis/tracker.py
src/xdevice/_core/analysis/wisecloud.py
src/xdevice/_core/cluster/__init__.py
src/xdevice/_core/cluster/__main__.py
src/xdevice/_core/cluster/models.py
src/xdevice/_core/cluster/runner.py
src/xdevice/_core/cluster/utils.py
src/xdevice/_core/cluster/controller/__init__.py
src/xdevice/_core/cluster/controller/api.py
src/xdevice/_core/cluster/controller/crud.py
src/xdevice/_core/cluster/controller/db.py
src/xdevice/_core/cluster/controller/handler.py
src/xdevice/_core/cluster/controller/main.py
src/xdevice/_core/cluster/worker/__init__.py
src/xdevice/_core/cluster/worker/api.py
src/xdevice/_core/cluster/worker/main.py
src/xdevice/_core/cluster/worker/task_manager.py
src/xdevice/_core/cluster/worker/task_runner.py
src/xdevice/_core/command/__init__.py
src/xdevice/_core/command/console.py
src/xdevice/_core/config/__init__.py
src/xdevice/_core/config/config_manager.py
src/xdevice/_core/config/resource_manager.py
src/xdevice/_core/context/__init__.py
src/xdevice/_core/context/abs.py
src/xdevice/_core/context/center.py
src/xdevice/_core/context/channel.py
src/xdevice/_core/context/handler.py
src/xdevice/_core/context/impl.py
src/xdevice/_core/context/life_stage.py
src/xdevice/_core/context/log.py
src/xdevice/_core/context/option_util.py
src/xdevice/_core/context/proxy.py
src/xdevice/_core/context/result.py
src/xdevice/_core/context/service.py
src/xdevice/_core/context/single.py
src/xdevice/_core/context/tdd.py
src/xdevice/_core/context/upload.py
src/xdevice/_core/driver/__init__.py
