Metadata-Version: 2.1
Name: xdevice
Version: 6.0.7.210
Summary: xdevice test framework
Home-page: UNKNOWN
License: UNKNOWN
Platform: UNKNOWN
Provides-Extra: full
